MANIFEST.in
README.md
setup.cfg
setup.py
linode_deploy_experimental/__init__.py
linode_deploy_experimental/__main__.py
linode_deploy_experimental/ssh.tcl
linode_deploy_experimental.egg-info/PKG-INFO
linode_deploy_experimental.egg-info/SOURCES.txt
linode_deploy_experimental.egg-info/dependency_links.txt
linode_deploy_experimental.egg-info/entry_points.txt
linode_deploy_experimental.egg-info/requires.txt
linode_deploy_experimental.egg-info/top_level.txt