Metadata-Version: 1.1
Name: linode-deploy-experimental
Version: 0.4
Summary: Deploy experimental disk images to Linode
Home-page: https://github.com/eatonphil/linode-deploy-experimental
Author: Phil Eaton
Author-email: UNKNOWN
License: UNKNOWN
Platform: UNKNOWN
Classifier: Development Status :: 3 - Alpha
Classifier: Environment :: Console
Classifier: Intended Audience :: Developers
Classifier: License :: OSI Approved :: BSD License
Classifier: Operating System :: MacOS :: MacOS X
Classifier: Operating System :: Unix
Classifier: Operating System :: POSIX
Classifier: Programming Language :: Python
Classifier: Programming Language :: Python :: 3
